noahs_pose_detector/__init__.py
noahs_pose_detector/pose_detector.py
noahs_pose_detector-0.1.0.dist-info/METADATA
noahs_pose_detector-0.1.0.dist-info/WHEEL
noahs_pose_detector-0.1.0.dist-info/top_level.txt
noahs_pose_detector-0.1.0.dist-info/RECORD
