Metadata-Version: 2.4
Name: noahs_pose_detector
Version: 0.1.0
Summary: A collection of tools related to pose detection in images
Author-email: Noah Jones <jonesnoah45010@gmail.com>
License: MIT
Project-URL: GitHub, https://github.com/jonesnoah45010/noahs_pose_detector
Classifier: Programming Language :: Python :: 3
Classifier: Operating System :: OS Independent
Classifier: License :: OSI Approved :: MIT License
Classifier: Intended Audience :: Developers
Classifier: Environment :: Console
Classifier: Topic :: Software Development :: Libraries :: Python Modules
Requires-Python: >=3.9
Requires-Dist: mediapipe
Requires-Dist: noahs_google_drive_downloader
Requires-Dist: opencv-python
Requires-Dist: numpy
